VariationalHMM/__init__.py
VariationalHMM/poisson_vhmm.py
VariationalHMM/vhmm_base.py
VariationalHMM-0.1.0.dist-info/LICENSE
VariationalHMM-0.1.0.dist-info/METADATA
VariationalHMM-0.1.0.dist-info/WHEEL
VariationalHMM-0.1.0.dist-info/top_level.txt
VariationalHMM-0.1.0.dist-info/RECORD
